descartes_rpa/__init__.py
descartes_rpa/analyze/__init__.py
descartes_rpa/analyze/analyze.py
descartes_rpa/convert/__init__.py
descartes_rpa/convert/loom.py
descartes_rpa/fetch/__init__.py
descartes_rpa/fetch/descartes.py
descartes_rpa/fetch/ensebml.py
descartes_rpa/io/__init__.py
descartes_rpa/io/load.py
descartes_rpa/io/save.py
descartes_rpa/pl/__init__.py
descartes_rpa/pl/pl.py
descartes_rpa/test/__init__.py
descartes_rpa/test/test_analyze.py
descartes_rpa/test/test_convert_data.py
descartes_rpa/test/test_fetch_data.py
descartes_rpa-1.2.1.dist-info/LICENSE
descartes_rpa-1.2.1.dist-info/METADATA
descartes_rpa-1.2.1.dist-info/WHEEL
descartes_rpa-1.2.1.dist-info/top_level.txt
descartes_rpa-1.2.1.dist-info/RECORD
