Metadata-Version: 2.1
Name: descartes-rpa
Version: 1.2.1
Summary: descartes_rpa: Extract pathway features from Single-Cell
Home-page: https://github.com/reactome/descartes_rpa
Author: Joao Luiz de Meirelles
Author-email: jldemeirelles@gmail.com
Requires-Python: >=3.8
License-File: LICENSE
Requires-Dist: scanpy (==1.7.2)
Requires-Dist: requests (==2.25.1)
Requires-Dist: aiohttp (==3.7.4)
Requires-Dist: flake8 (==3.9.2)
Requires-Dist: loompy (==3.0.6)
Requires-Dist: reactome2py (==3.0.0)
Requires-Dist: seaborn (==0.11.1)
Requires-Dist: scikit-learn (==0.24.2)
Requires-Dist: statsmodels (==0.12.2)
Requires-Dist: numba (==0.53.1)
Requires-Dist: tables (==3.6.1)
Requires-Dist: python-igraph (==0.9.1)
Requires-Dist: leidenalg (==0.8.4)
Requires-Dist: UpSetPlot (==0.6.1)
Requires-Dist: matplotlib (==3.5.2)
